{"config": {"view": {"continuousWidth": 300, "continuousHeight": 300}, "locale": {"number": {"decimal": ",", "thousands": ".", "grouping": [3], "currency": ["", "\u00a0\u20ac"]}}, "title": {"dx": 30, "dy": -15, "fontSize": 15}}, "data": {"name": "data-37ac5c82b89a5b08bae6872d3a19b3c3"}, "facet": {"column": {"field": "seg2", "header": {"labelFontSize": 15}, "sort": {"field": "order"}, "title": null, "type": "nominal"}, "row": {"field": "row", "header": {"labels": false}, "sort": {"field": "order"}, "title": null, "type": "nominal"}}, "spec": {"layer": [{"mark": {"type": "errorbar", "ticks": {"width": 10}}, "encoding": {"tooltip": {"value": null}, "y": {"axis": {"labelFontSize": 11}, "field": "lower", "title": null, "type": "quantitative"}, "y2": {"field": "upper"}}}, {"mark": {"type": "line", "point": {"size": 50}}, "encoding": {"tooltip": [{"field": "seg1", "title": "Grupo", "type": "nominal"}, {"field": "mean", "format": ".2f", "title": "Media", "type": "quantitative"}, {"field": "lower", "format": ".2f", "title": "L\u00edmite inferior", "type": "quantitative"}, {"field": "upper", "format": ".2f", "title": "L\u00edmite superior", "type": "quantitative"}], "y": {"axis": {"labelFontSize": 11}, "field": "mean", "title": null, "type": "quantitative"}}, "name": "view_71"}], "encoding": {"color": {"field": "seg1", "legend": {"labelFontSize": 12, "symbolSize": 400}, "sort": {"field": "order"}, "title": null, "type": "nominal"}, "x": {"axis": {"labelAngle": 30, "labelFontSize": 11}, "field": "M", "sort": {"field": "order"}, "title": null, "type": "nominal"}, "xOffset": {"field": "seg1", "scale": {"paddingOuter": 0.5}, "sort": {"field": "order"}, "type": "nominal"}}, "height": 175, "width": {"step": 45, "for": "position"}}, "params": [{"name": "param_187", "select": {"type": "interval", "encodings": ["x", "y"]}, "bind": "scales", "views": ["view_71"]}], "resolve": {"axis": {"x": "independent", "y": "independent"}, "scale": {"xOffset": "independent"}}, "title": {"text": ["Bienestar emocional - Nerviosismo escala 0-10 por regi\u00f3n, sexo y nivel de estudios (medias e intervalos de confianza al 95%)"], "subtitle": "Fuente: Proyecto DAS-EP, EXPEDIENTE ISCIII - PI22/01051 y PI22/00512. C\u00f3digo de variable: NERVIOSISMO"}, "transform": [{"calculate": "datum.seg1 == 'Total'", "as": "row"}, {"filter": "true == true"}], "$schema": "https://vega.github.io/schema/vega-lite/v5.17.0.json", "datasets": {"data-37ac5c82b89a5b08bae6872d3a19b3c3": [{"M": "Pa\u00eds Vasco", "seg1": "Hombre", "seg2": "Hasta primaria", "mean": 3.1270813566594997, "lower": 2.7443383993508457, "upper": 3.5940771268253555, "order": 0}, {"M": "Pa\u00eds Vasco", "seg1": "Hombre", "seg2": "Secundaria", "mean": 2.907026255696091, "lower": 2.7827862246146546, "upper": 3.0494225952524414, "order": 1}, {"M": "Pa\u00eds Vasco", "seg1": "Hombre", "seg2": "Estudios universitarios", "mean": 2.7263117385528384, "lower": 2.5041053890579983, "upper": 2.9524211104631735, "order": 2}, {"M": "Pa\u00eds Vasco", "seg1": "Hombre", "seg2": "Total", "mean": 2.8914113601228713, "lower": 2.7766452366386907, "upper": 3.0131567107040134, "order": 3}, {"M": "Pa\u00eds Vasco", "seg1": "Mujer", "seg2": "Hasta primaria", "mean": 3.769111354674824, "lower": 3.4824930667432827, "upper": 4.076817346074686, "order": 4}, {"M": "Pa\u00eds Vasco", "seg1": "Mujer", "seg2": "Secundaria", "mean": 3.5712181341948055, "lower": 3.4147402729019682, "upper": 3.7308455364918474, "order": 5}, {"M": "Pa\u00eds Vasco", "seg1": "Mujer", "seg2": "Estudios universitarios", "mean": 3.3222354070430637, "lower": 3.111163950625772, "upper": 3.5198782482591082, "order": 6}, {"M": "Pa\u00eds Vasco", "seg1": "Mujer", "seg2": "Total", "mean": 3.539396491552226, "lower": 3.422063273527736, "upper": 3.6599102367337837, "order": 7}, {"M": "Pa\u00eds Vasco", "seg1": "Total", "seg2": "Hasta primaria", "mean": 3.527318464479108, "lower": 3.2910297284988776, "upper": 3.786108941086038, "order": 8}, {"M": "Pa\u00eds Vasco", "seg1": "Total", "seg2": "Secundaria", "mean": 3.242876230861842, "lower": 3.1337420970490975, "upper": 3.3438060330983, "order": 9}, {"M": "Pa\u00eds Vasco", "seg1": "Total", "seg2": "Estudios universitarios", "mean": 3.0655212985544593, "lower": 2.923077797096024, "upper": 3.218725131332391, "order": 10}, {"M": "Pa\u00eds Vasco", "seg1": "Total", "seg2": "Total", "mean": 3.2404682769601347, "lower": 3.1437293794672887, "upper": 3.3259239430019303, "order": 11}, {"M": "Andalucia", "seg1": "Hombre", "seg2": "Hasta primaria", "mean": 7.106529967373431, "lower": 6.761634117298668, "upper": 7.381514510000181, "order": 12}, {"M": "Andalucia", "seg1": "Hombre", "seg2": "Secundaria", "mean": 8.268092589604812, "lower": 7.8586471763251335, "upper": 9.020504994860989, "order": 13}, {"M": "Andalucia", "seg1": "Hombre", "seg2": "Estudios universitarios", "mean": 7.948156301574618, "lower": 7.69321322634243, "upper": 8.13622839962285, "order": 14}, {"M": "Andalucia", "seg1": "Hombre", "seg2": "Total", "mean": 8.071071674321724, "lower": 7.786297078845048, "upper": 8.681134640113537, "order": 15}, {"M": "Andalucia", "seg1": "Mujer", "seg2": "Hasta primaria", "mean": 6.663138056684911, "lower": 6.439733242142966, "upper": 6.8887688691083895, "order": 16}, {"M": "Andalucia", "seg1": "Mujer", "seg2": "Secundaria", "mean": 6.784276714269435, "lower": 5.151716573911263, "upper": 7.74034701270233, "order": 17}, {"M": "Andalucia", "seg1": "Mujer", "seg2": "Estudios universitarios", "mean": 7.308601618180127, "lower": 7.10733539571231, "upper": 7.516545541661217, "order": 18}, {"M": "Andalucia", "seg1": "Mujer", "seg2": "Total", "mean": 6.866971306099144, "lower": 5.426853704090606, "upper": 7.422176321878073, "order": 19}, {"M": "Andalucia", "seg1": "Total", "seg2": "Hasta primaria", "mean": 6.825072017548643, "lower": 6.65650713632481, "upper": 7.005502820651524, "order": 20}, {"M": "Andalucia", "seg1": "Total", "seg2": "Secundaria", "mean": 7.53252975036068, "lower": 6.194990067418351, "upper": 8.175527209585912, "order": 21}, {"M": "Andalucia", "seg1": "Total", "seg2": "Estudios universitarios", "mean": 7.634194885388094, "lower": 7.459869781172357, "upper": 7.792758560981865, "order": 22}, {"M": "Andalucia", "seg1": "Total", "seg2": "Total", "mean": 7.451080172566385, "lower": 6.382236524053761, "upper": 7.840389001781131, "order": 23}, {"M": "C.Valenciana", "seg1": "Hombre", "seg2": "Hasta primaria", "mean": 5.595995293497499, "lower": 5.296330623093432, "upper": 5.848020460798721, "order": 24}, {"M": "C.Valenciana", "seg1": "Hombre", "seg2": "Secundaria", "mean": 6.238214850757794, "lower": 6.118167214473297, "upper": 6.357996602901274, "order": 25}, {"M": "C.Valenciana", "seg1": "Hombre", "seg2": "Estudios universitarios", "mean": 5.784907536855959, "lower": 5.595106592430337, "upper": 5.997119307863859, "order": 26}, {"M": "C.Valenciana", "seg1": "Hombre", "seg2": "Total", "mean": 6.025302663299963, "lower": 5.922692311619183, "upper": 6.117593662157076, "order": 27}, {"M": "C.Valenciana", "seg1": "Mujer", "seg2": "Hasta primaria", "mean": 5.585468389003388, "lower": 5.324841773844345, "upper": 5.824996655419406, "order": 28}, {"M": "C.Valenciana", "seg1": "Mujer", "seg2": "Secundaria", "mean": 6.597317038516744, "lower": 6.462424654514441, "upper": 6.727117827880665, "order": 29}, {"M": "C.Valenciana", "seg1": "Mujer", "seg2": "Estudios universitarios", "mean": 6.107791922069513, "lower": 5.8971948231898565, "upper": 6.305494785865263, "order": 30}, {"M": "C.Valenciana", "seg1": "Mujer", "seg2": "Total", "mean": 6.2894030443507605, "lower": 6.183024466079172, "upper": 6.393031467262167, "order": 31}, {"M": "C.Valenciana", "seg1": "Total", "seg2": "Hasta primaria", "mean": 5.590112159467735, "lower": 5.4145827911965, "upper": 5.773068995095858, "order": 32}, {"M": "C.Valenciana", "seg1": "Total", "seg2": "Secundaria", "mean": 6.418644266524661, "lower": 6.330728105586734, "upper": 6.506679541607136, "order": 33}, {"M": "C.Valenciana", "seg1": "Total", "seg2": "Estudios universitarios", "mean": 5.954204149893123, "lower": 5.819821062926962, "upper": 6.09910513321888, "order": 34}, {"M": "C.Valenciana", "seg1": "Total", "seg2": "Total", "mean": 6.16193672424469, "lower": 6.083651893122621, "upper": 6.227583381986477, "order": 35}, {"M": "Barcelona", "seg1": "Hombre", "seg2": "Hasta primaria", "mean": 6.780891322937318, "lower": 6.27207451318862, "upper": 7.322993887253215, "order": 36}, {"M": "Barcelona", "seg1": "Hombre", "seg2": "Secundaria", "mean": 6.337754757572226, "lower": 6.141506338319097, "upper": 6.541966455644053, "order": 37}, {"M": "Barcelona", "seg1": "Hombre", "seg2": "Estudios universitarios", "mean": 6.484786186229112, "lower": 6.224826580124593, "upper": 6.693647013406984, "order": 38}, {"M": "Barcelona", "seg1": "Hombre", "seg2": "Total", "mean": 6.440578224431206, "lower": 6.264790588756757, "upper": 6.590160562165737, "order": 39}, {"M": "Barcelona", "seg1": "Mujer", "seg2": "Hasta primaria", "mean": 6.338690703391003, "lower": 5.565492377173062, "upper": 6.990599144202799, "order": 40}, {"M": "Barcelona", "seg1": "Mujer", "seg2": "Secundaria", "mean": 5.447554376064318, "lower": 5.221502492840424, "upper": 5.668060461772892, "order": 41}, {"M": "Barcelona", "seg1": "Mujer", "seg2": "Estudios universitarios", "mean": 5.912113855445382, "lower": 5.691136141914412, "upper": 6.141204598096009, "order": 42}, {"M": "Barcelona", "seg1": "Mujer", "seg2": "Total", "mean": 5.736021872741828, "lower": 5.575118524091004, "upper": 5.892789345419045, "order": 43}, {"M": "Barcelona", "seg1": "Total", "seg2": "Hasta primaria", "mean": 6.548634933194625, "lower": 6.0827003322089155, "upper": 7.011359531578223, "order": 44}, {"M": "Barcelona", "seg1": "Total", "seg2": "Secundaria", "mean": 5.891922162857796, "lower": 5.731202329250818, "upper": 6.047961130552989, "order": 45}, {"M": "Barcelona", "seg1": "Total", "seg2": "Estudios universitarios", "mean": 6.164142515278247, "lower": 5.991233346164751, "upper": 6.325277024518752, "order": 46}, {"M": "Barcelona", "seg1": "Total", "seg2": "Total", "mean": 6.0702459977750785, "lower": 5.959536973812635, "upper": 6.18723248055326, "order": 47}]}}